{
  "content": "• Hacker News: Pre-emptive Z80 multitasking explainer\n • Hacker News: Artifact (YC W25) is hiring engineers in NYC to build modern ECAD\n • tagesschau.de (RSS): tagesschau.de - die erste Adresse für Nachrichten und Information\n • tagesschau.de (RSS): Studie: KI-Chatbots lügen bei 40 Prozent der Antworten",
  "hash": "f009f2140a11453e16358c7d79b21cc85c80df217e0a8c68f4aedf3c55bf4083",
  "id": "BLK_1761575463_n29w97",
  "meta": {},
  "pubkey": "PBMCp2XBiUntTrU3C6OXrXuJv7X68LTVh1MR9gLqAtk=",
  "signature": "QFrcMvfNJJ6bROX24B7OYWhY9dslLUH4wlRNviDZZBrZ6cutH8xYyJx3fpefdc4sU3KPHMudrBV1mMYtKTEIDQ==",
  "signed_at": "2025-10-27T14:31:03Z",
  "tags": [
    "digest",
    "web",
    "news"
  ],
  "title": "Web Digest 2025-10-27 15:31",
  "ts": 1761575463,
  "url": ""
}