{
  "id": "BLK_1758997335_46c6d8",
  "title": "Web Digest 2025-09-27 20:22",
  "content": "• Hacker News: Americans Are Using PTO to Sleep, Not for Vacation–Report\n • Hacker News: Great Question (YC W21) Is Hiring Director of Product\n • tagesschau.de (RSS): tagesschau.de - die erste Adresse für Nachrichten und Information\n • tagesschau.de (RSS): Trump will Militär nach Portland schicken",
  "tags": [
    "digest",
    "web",
    "news"
  ],
  "url": null,
  "created_at": 1758997335.6062768,
  "meta": {
    "source": "skill:web_digest"
  },
  "path": null,
  "score": null
}