{
  "content": "• Hacker News: Generative AI's Energy Needs Are Reshaping Our World\n • Hacker News: Germany outfitted half a million balconies with solar panels\n • tagesschau.de (RSS): tagesschau.de - die erste Adresse für Nachrichten und Information\n • tagesschau.de (RSS): Merz vermutet Russland hinter vielen Drohnen-Flügen",
  "created_at": 1759712568.4396827,
  "hash": "96883c540d8f8f42d9b92703c2b7c26d99a05d826272b63270d1c604b93c3511",
  "id": "BLK_1759712568_4e1024",
  "meta": {
    "source": "skill:web_digest"
  },
  "path": null,
  "pubkey": "PBMCp2XBiUntTrU3C6OXrXuJv7X68LTVh1MR9gLqAtk=",
  "score": null,
  "signature": "otIMH780+Um9i6HUwReizQyC/nAfCAYcnpQmwTyJJ/wOxHeI3C9fTNMipbXvBKWcWUj+mm3m8UsDRrcngCm8Aw==",
  "signed_at": "2025-10-29T12:53:42Z",
  "tags": [
    "digest",
    "web",
    "news"
  ],
  "title": "Web Digest 2025-10-06 03:02",
  "url": null
}