{
  "content": "• Hacker News: My Ed(1) Toolbox\n • Hacker News: US Airlines Push to Strip Away Travelers' Rights by Rolling Back Key Protections\n • tagesschau.de (RSS): tagesschau.de - die erste Adresse für Nachrichten und Information\n • tagesschau.de (RSS): Trumps Rede voller Falschbehauptungen bei UN-Vollversammlung",
  "hash": "62e9fc0cd226092ea98a878c26ca64a21c8cf26114f4eb3b7f331d3a8137d5ba",
  "id": "BLK_1758719372_7srim2",
  "meta": {},
  "pubkey": "PBMCp2XBiUntTrU3C6OXrXuJv7X68LTVh1MR9gLqAtk=",
  "signature": "NKhlSA1nQrIv0qWdV4BMFTY2O7AI7ubH//7uzHR1L1zSojGOrIQdY9euSO/LPhIgyYI5Ws1E+z67n6Zlzl1nBw==",
  "signed_at": "2025-11-05T10:06:06Z",
  "tags": [
    "digest",
    "web",
    "news"
  ],
  "title": "Web Digest 2025-09-24 15:09",
  "ts": 1758719372,
  "url": ""
}