{
  "id": "BLK_1758609150_4zdmeo",
  "title": "Web Digest 2025-09-23 08:32",
  "content": "• Hacker News: Delete FROM users WHERE location = 'Iran';\n • Hacker News: Zoxide: A Better CD Command\n • tagesschau.de (RSS): tagesschau.de - die erste Adresse für Nachrichten und Information\n • tagesschau.de (RSS): Anerkennung von Palästina: \"Die Zeit für Frieden ist gekommen\"",
  "tags": [
    "digest",
    "web",
    "news"
  ],
  "url": "",
  "ts": 1758609150,
  "meta": {},
  "hash": "cbb0d4bd8fbd4e91348eff5d926f2ce0b2bcfe9990bd7a4ff67d2d65ec78a227"
}