{
  "content": "• Hacker News: Hurricane category 6 could be introduced under new storm severity scale\n • Hacker News: Enrollment at trade schools is expected to grow 6.6% a year\n • tagesschau.de (RSS): tagesschau.de - die erste Adresse für Nachrichten und Information\n • tagesschau.de (RSS): Arbeitsministerin Bas für weitere Nullrunde beim Bürgergeld",
  "hash": "f16fc27ccf7ae2d4808bfc3822aa2dd16e97487ae5c788d1cda40efef3fb0763",
  "id": "BLK_1756601599_ppwnm8",
  "meta": {},
  "pubkey": "PBMCp2XBiUntTrU3C6OXrXuJv7X68LTVh1MR9gLqAtk=",
  "signature": "kc8v8Vkisg6VgPXdo1U0D/qC2XG5tPkyChwRf7/Yb0bcLe5d4zHSzAlmbFQvVYesnw+A3vdZJ3EyoL53KlgJAA==",
  "signed_at": "2025-11-05T10:06:06Z",
  "tags": [
    "digest",
    "web",
    "news"
  ],
  "title": "Web Digest 2025-08-31 02:53",
  "ts": 1756601599,
  "url": ""
}