{
  "content": "• Hacker News: ETFs now hold more than $3.1T worth of just top US companies\n • Hacker News: Scottish brothers finish mammoth row across Pacific Ocean after 139 days\n • tagesschau.de (RSS): tagesschau.de - die erste Adresse für Nachrichten und Information\n • tagesschau.de (RSS): Putin reist nach China - und hofft auf stärkere Zusammenarbeit",
  "created_at": 1756608803.2840123,
  "hash": "f353aa304a34a252e775b16ad43ec08cb178d2221727fbc6f87d720c62ed3785",
  "id": "BLK_1756608803_43b78f",
  "meta": {
    "source": "skill:web_digest"
  },
  "path": null,
  "pubkey": "PBMCp2XBiUntTrU3C6OXrXuJv7X68LTVh1MR9gLqAtk=",
  "score": null,
  "signature": "/4+8KmKheP6tHJCFhDUfD04qO+bc+7X31qkfpPvmIwVCc1cNh4IsdDsIH5mWekKW07+3JsuLg63Wl6ur6jqVAg==",
  "signed_at": "2025-11-05T10:06:07Z",
  "tags": [
    "digest",
    "web",
    "news"
  ],
  "title": "Web Digest 2025-08-31 04:53",
  "url": null
}