{
  "content": "• Hacker News: How to Stop Functional Programming\n • Hacker News: New thermoelectric cooling breakthrough nearly doubles efficiency\n • tagesschau.de (RSS): tagesschau.de - die erste Adresse für Nachrichten und Information\n • tagesschau.de (RSS): Großbritannien, Kanada und Australien erkennen Palästinenserstaat an",
  "created_at": 1758469022.0494597,
  "hash": "8fad2900ff70d5b7d7a43214a34c13d4b65ab329aaa9025a1a20fbb03488b299",
  "id": "BLK_1758469022_651a09",
  "meta": {
    "source": "skill:web_digest"
  },
  "path": null,
  "pubkey": "PBMCp2XBiUntTrU3C6OXrXuJv7X68LTVh1MR9gLqAtk=",
  "score": null,
  "signature": "bqHMoN+ESce93v3EwyCPf5AcS4jEj39Lx8HuVdB/XhsVZpZrmYLe+sCB/FLncwZ8bG/jjAf6o6jLSYysfwmIBQ==",
  "signed_at": "2025-10-29T12:53:42Z",
  "tags": [
    "digest",
    "web",
    "news"
  ],
  "title": "Web Digest 2025-09-21 17:37",
  "url": null
}