{
  "content": "• Hacker News: React Flow, open source libraries for node-based UIs with React or Svelte\n • Hacker News: Introduction to the concept of likelihood and its applications (2018)\n • tagesschau.de (RSS): tagesschau.de - die erste Adresse für Nachrichten und Information\n • tagesschau.de (RSS): Minimalkompromiss bei Verwendung von russischem Geld",
  "hash": "e4067e0a7af2444fea9ea669505b5f6d6c134bfac0295057a9c65a3c0749936e",
  "id": "BLK_1761265932_nrngzi",
  "meta": {},
  "pubkey": "PBMCp2XBiUntTrU3C6OXrXuJv7X68LTVh1MR9gLqAtk=",
  "signature": "VWhmSLIGPYLACoMkMs+99eQHZoQAoLZ/giF4XfoUx5f5kdXTUVN9OF9gr6DEIp1yYNg+523H36WZnZz/n9biDQ==",
  "signed_at": "2025-10-24T00:32:12Z",
  "tags": [
    "digest",
    "web",
    "news"
  ],
  "title": "Web Digest 2025-10-24 02:32",
  "ts": 1761265932,
  "url": ""
}