{
  "content": "• Hacker News: The App Store Was Always Authoritarian\n • Hacker News: Spyware maker NSO Group confirms acquisition by US investors\n • tagesschau.de (RSS): tagesschau.de - die erste Adresse für Nachrichten und Information\n • tagesschau.de (RSS): Terrorgruppe Hamas bestätigt Geisel-Freilassung am Montag",
  "hash": "5dbcef0e617690efd607a4061f6518d3feb7cf79866567ca37736cb44ed999bb",
  "id": "BLK_1760256419_3tfalr",
  "meta": {},
  "pubkey": "PBMCp2XBiUntTrU3C6OXrXuJv7X68LTVh1MR9gLqAtk=",
  "signature": "SeHcggjResVHQdwQ/BDuppl4gywQ9G2jC7GAHEYHgkfMMYp8YogzzSnPZsPllESwcwtAvo2A2QScYsrlRsaaAg==",
  "signed_at": "2025-11-05T10:06:07Z",
  "tags": [
    "digest",
    "web",
    "news"
  ],
  "title": "Web Digest 2025-10-12 10:06",
  "ts": 1760256419,
  "url": ""
}