{
  "content": "• Hacker News: Meta bypassed Apple privacy protections, claims former employee\n • Hacker News: Apple has a private CSS property to add Liquid Glass effects to web content\n • tagesschau.de (RSS): tagesschau.de - die erste Adresse für Nachrichten und Information\n • tagesschau.de (RSS): Kommt mit dem Wehrdienst der Zivildienst zurück?",
  "created_at": 1757950445.6678019,
  "hash": "77e55c88b4bba65071e78847e926917b9cc9a9c7c6a6f97650f7ac341e8e0b85",
  "id": "BLK_1757950445_ac9b15",
  "meta": {
    "source": "skill:web_digest"
  },
  "path": null,
  "pubkey": "PBMCp2XBiUntTrU3C6OXrXuJv7X68LTVh1MR9gLqAtk=",
  "score": null,
  "signature": "BOXvZTvRNkozhDD4U6B1GiPqAHUTLMVz+dxB2M9C9dj4pAqEcZCvZTH8ipG3neXw3fi7L3dgonjK0cGFroRlCA==",
  "signed_at": "2025-09-21T08:13:36Z",
  "tags": [
    "digest",
    "web",
    "news"
  ],
  "title": "Web Digest 2025-09-15 17:34",
  "url": null
}