{
  "content": "• Hacker News: \"Be Different\" doesn't work for building products anymore\n • Hacker News: Launch HN: Grapevine (YC S19) – A company GPT that actually works\n • tagesschau.de (RSS): tagesschau.de - die erste Adresse für Nachrichten und Information\n • tagesschau.de (RSS): Wohnraummangel: Kann der \"Bau-Turbo\" schnell Wohnraum schaffen?",
  "created_at": 1759768391.8363354,
  "hash": "226938b41b6aaffee04ec8671f9a89c84ed80f283d5ee58804882eb321b11b9e",
  "id": "BLK_1759768391_5a21a5",
  "meta": {
    "source": "skill:web_digest"
  },
  "path": null,
  "pubkey": "PBMCp2XBiUntTrU3C6OXrXuJv7X68LTVh1MR9gLqAtk=",
  "score": null,
  "signature": "tmAgpj0dxHNYHZihA64SSlJN9ua23T8mWkUWxGDdxhKUjj0PHAjtbH/rjq75HfOWmf4SmIZU8cevJgqvpHiQAA==",
  "signed_at": "2025-10-29T12:53:42Z",
  "tags": [
    "digest",
    "web",
    "news"
  ],
  "title": "Web Digest 2025-10-06 18:33",
  "url": null
}