{
  "content": "• Hacker News: I tracked Amazon's Prime Day prices. We've been played\n • Hacker News: I Switched from Htmx to Datastar\n • tagesschau.de (RSS): tagesschau.de - die erste Adresse für Nachrichten und Information\n • tagesschau.de (RSS): Gazastreifen: US-Soldaten sollen Waffenruhe überwachen",
  "hash": "731b693da50a3799fae7b792455042aea8b222b860cbcfb430028a9fa126970b",
  "id": "BLK_1760085331_swcfge",
  "meta": {},
  "pubkey": "PBMCp2XBiUntTrU3C6OXrXuJv7X68LTVh1MR9gLqAtk=",
  "signature": "doo+3XAPlcjKZ8Okj/Zpif4KVHH89YO8TyL+/wFvx+7v0MG1Dqk4QpvBBjxiSU627lRXRD3BRdeUyAiAen77DQ==",
  "signed_at": "2025-11-05T10:06:07Z",
  "tags": [
    "digest",
    "web",
    "news"
  ],
  "title": "Web Digest 2025-10-10 10:35",
  "ts": 1760085331,
  "url": ""
}