{
  "content": "• Hacker News: A motto for programmers: \"Tuere usorem, data, veritatem\"\n • Hacker News: Kapa.ai (YC S23) is hiring research and software engineers\n • tagesschau.de (RSS): tagesschau.de - die erste Adresse für Nachrichten und Information\n • tagesschau.de (RSS): Nach PayPal-Panne: Welche Alternativen es zum US-Zahlungsdienst gibt",
  "hash": "5fb49e59c641632624174da1116b0bb50ddc97b17134f54183f637ac185dd859",
  "id": "BLK_1756806110_7mmzzv",
  "meta": {},
  "pubkey": "PBMCp2XBiUntTrU3C6OXrXuJv7X68LTVh1MR9gLqAtk=",
  "signature": "EgfHurSqDCtEHbhY0euoITv1pdPt9U5Q2wntlZRa4Qw4faE9GZ1Ox1aAsWUCV/K1tN6IWaTFQw0jGRPseTxVCA==",
  "signed_at": "2025-09-21T08:13:36Z",
  "tags": [
    "digest",
    "web",
    "news"
  ],
  "title": "Web Digest 2025-09-02 11:41",
  "ts": 1756806110,
  "url": ""
}