{
  "content": "• Hacker News: Nobel Prize in Chemistry 2025\n • Hacker News: Buy European: EU Commissions New Apply AI Strategy Launched\n • tagesschau.de (RSS): tagesschau.de - die erste Adresse für Nachrichten und Information\n • tagesschau.de (RSS): \"Molekulare Architektur\": Drei Forscher erhalten Chemie-Nobelpreis",
  "created_at": 1759919656.5702467,
  "hash": "5d9d1cf394736a9c1ff26d6df78f1ef281fc9c8835038d560a113a11df489013",
  "id": "BLK_1759919656_6fcc87",
  "meta": {
    "source": "skill:web_digest"
  },
  "path": null,
  "pubkey": "+KeRyg05RDtAos8dbZHUHgxehr7E38sPW6tEWbpAnFw=",
  "score": null,
  "signature": "rADvj723/n9KI6clI5hBhgHDdig8sT0r2nQR+TgAApQRBFuTPabvr/KBcAAzpXJv+VLvEybUkDIoh1P1sdS1Cw==",
  "signed_at": "2025-10-22T11:39:33Z",
  "tags": [
    "digest",
    "web",
    "news"
  ],
  "title": "Web Digest 2025-10-08 12:34",
  "url": null
}