{
  "id": "BLK_1758883866_4dpbgh",
  "title": "Web Digest 2025-09-26 12:51",
  "content": "• Hacker News: Show HN: The Little Notebook for Learning Linear Algebra with Python\n • Hacker News: Pop OS is getting beta\n • tagesschau.de (RSS): tagesschau.de - die erste Adresse für Nachrichten und Information\n • tagesschau.de (RSS): EU sieht Pharmaexporte vor neuen US-Zöllen geschützt",
  "tags": [
    "digest",
    "web",
    "news"
  ],
  "url": "",
  "ts": 1758883866,
  "meta": {},
  "hash": "ef0f4858455c2a25f7241181e42c133fb3e2dc7a489dd559813d7802e38af700"
}