{
  "content": "• Hacker News: Environment variables are a legacy mess: Let's dive deep into them\n • Hacker News: $19B Wiped Out in Crypto's Biggest Liquidation\n • tagesschau.de (RSS): tagesschau.de - die erste Adresse für Nachrichten und Information\n • tagesschau.de (RSS): Die deutschen Geheimdienstchefs warnen deutlich vor Russland",
  "hash": "430b54fdc7d5ceeb41e261fd60d7def7fea978cb352ccc6b36ec67c5d1839e22",
  "id": "BLK_1760375279_ldzida",
  "meta": {},
  "pubkey": "PBMCp2XBiUntTrU3C6OXrXuJv7X68LTVh1MR9gLqAtk=",
  "signature": "uZBuLLCdYmvIFIPCHAqwP3Q7wEidUFLq0CyTTUlUweD/nyf3u9gyLRfM+hPep5UYs6owzcap5Z9l0p9gCM9+Bg==",
  "signed_at": "2025-11-05T10:06:06Z",
  "tags": [
    "digest",
    "web",
    "news"
  ],
  "title": "Web Digest 2025-10-13 19:07",
  "ts": 1760375279,
  "url": ""
}