{
  "content": "• Hacker News: Unofficial Windows 11 requirements bypass tool allows disabling all AI features\n • Hacker News: RFC 3339 vs. ISO 8601\n • tagesschau.de (RSS): tagesschau.de - die erste Adresse für Nachrichten und Information\n • tagesschau.de (RSS): Massive Angriffe auf Ukraine - Regierungsgebäude in Kiew brennt",
  "created_at": 1757229151.9899316,
  "hash": "319097de878daf04c95ae531864d1c30416a8a2ce578194b8b616806ae8c446b",
  "id": "BLK_1757229151_e5cf98",
  "meta": {
    "source": "skill:web_digest"
  },
  "path": null,
  "pubkey": "PBMCp2XBiUntTrU3C6OXrXuJv7X68LTVh1MR9gLqAtk=",
  "score": null,
  "signature": "UoaQeN88hBxBYk++6K9XVq1DA3z/u2r8isSdt009Rlj/agpEKxH74oum4kr84L6CD/WvlkDh24ZcISGZ38BNBw==",
  "signed_at": "2025-09-21T08:13:36Z",
  "tags": [
    "digest",
    "web",
    "news"
  ],
  "title": "Web Digest 2025-09-07 09:12",
  "url": null
}