{
  "content": "• Hacker News: Bitmovin (YC S15) Is Hiring Engineering ICs and Managers in Europe\n • Hacker News: Tsdown – The Elegant Bundler for Libraries\n • tagesschau.de (RSS): tagesschau.de - die erste Adresse für Nachrichten und Information\n • tagesschau.de (RSS): Trump nimmt zum Auftakt seiner Asien-Reise an ASEAN-Gipfel teil",
  "hash": "b3c401772e17aaaf10fdaa3b002bc6841ab72c2c893c93f275ecfd76511b3665",
  "id": "BLK_1761467113_8uko3m",
  "meta": {},
  "pubkey": "PBMCp2XBiUntTrU3C6OXrXuJv7X68LTVh1MR9gLqAtk=",
  "signature": "mWChOo6uFrf3gQk92Y3ZnuS6EiBNMQqQqI0BKA+8pWOg9MrEENoNNoM5PWeq9ByW2hOeJegDwmvxD/Ml9SVCDw==",
  "signed_at": "2025-10-26T08:25:13Z",
  "tags": [
    "digest",
    "web",
    "news"
  ],
  "title": "Web Digest 2025-10-26 09:25",
  "ts": 1761467113,
  "url": ""
}