{
  "content": "• Hacker News: Kapa.ai (YC S23) Is Hiring a Customer Solutions Engineer (EU Remote)\n • Hacker News: No reachable chess position with more than 218 moves\n • tagesschau.de (RSS): tagesschau.de - die erste Adresse für Nachrichten und Information\n • tagesschau.de (RSS): Sabotagefälle bei der Deutschen Bahn - wer steckt dahinter?",
  "hash": "1e62f71f491fe4af004169cf3fdd2052c7c4bf4fece7be93b7f81cce62065631",
  "id": "BLK_1758872260_s21spe",
  "meta": {},
  "pubkey": "PBMCp2XBiUntTrU3C6OXrXuJv7X68LTVh1MR9gLqAtk=",
  "signature": "XvqHUMS68e5ymBympv8sURxpGnsMTKid9Jl+0g+hOXRtLvgX7KdYncciglDPljO34GID48PwL04z8f3z5/D5Cw==",
  "signed_at": "2025-10-29T12:53:42Z",
  "tags": [
    "digest",
    "web",
    "news"
  ],
  "title": "Web Digest 2025-09-26 09:37",
  "ts": 1758872260,
  "url": ""
}