{
  "content": "• Hacker News: Guy is running a Google rival from his laundry room\n • Hacker News: Windows 10 resists its end: usage share climbs while Windows 11's falls\n • tagesschau.de (RSS): tagesschau.de - die erste Adresse für Nachrichten und Information\n • tagesschau.de (RSS): Drohnen über Polen - was bedeutet das?",
  "hash": "db450a70153c6ce47ada6181836977b73fb2d5d2d34671ec411b9e516991d8df",
  "id": "BLK_1757511904_svm8kn",
  "meta": {},
  "pubkey": "PBMCp2XBiUntTrU3C6OXrXuJv7X68LTVh1MR9gLqAtk=",
  "signature": "Tjo2L84YyxTrtunUZQZi1kaaEk9ybdFwxSgHrejhTH+TUhPL8Giti86gPKSXcY2MLC4z0L3ce2/9eQc/aQOFDw==",
  "signed_at": "2025-11-05T10:06:06Z",
  "tags": [
    "digest",
    "web",
    "news"
  ],
  "title": "Web Digest 2025-09-10 15:45",
  "ts": 1757511904,
  "url": ""
}