{
  "content": "• Hacker News: A motto for programmers: \"Tuere usorem, data, veritatem\"\n • Hacker News: Kapa.ai (YC S23) is hiring research and software engineers\n • tagesschau.de (RSS): tagesschau.de - die erste Adresse für Nachrichten und Information\n • tagesschau.de (RSS): Nach PayPal-Panne: Welche Alternativen es zum US-Zahlungsdienst gibt",
  "created_at": 1756804002.1108148,
  "hash": "e7a29df277e608ca42fb79479a5acdcf21a08a334057b1c0856e20fe4b316e04",
  "id": "BLK_1756804002_c6ca95",
  "meta": {
    "source": "skill:web_digest"
  },
  "path": null,
  "pubkey": "PBMCp2XBiUntTrU3C6OXrXuJv7X68LTVh1MR9gLqAtk=",
  "score": null,
  "signature": "PbJ4dAenS8XW4zC1irP4TDKV5drBL0CSNUWG/3hS3KPhHbdlnSmG1UiElECzCXz3kKfxwfib96YaEYagComSDg==",
  "signed_at": "2025-11-05T10:06:06Z",
  "tags": [
    "digest",
    "web",
    "news"
  ],
  "title": "Web Digest 2025-09-02 11:06",
  "url": null
}