{
  "content": "• Hacker News: iFixIt iPhone Air Teardown\n • Hacker News: Radar and Radio Failures at Dallas Area Airports\n • tagesschau.de (RSS): tagesschau.de - die erste Adresse für Nachrichten und Information\n • tagesschau.de (RSS): Katerstimmung bei den Vereinten Nationen vor Vollversammlung",
  "created_at": 1758427896.1249666,
  "hash": "257a2d85de47f35f9a8ba3966e4dfb5ee0373e0f95b99c7b290c5041b69278ce",
  "id": "BLK_1758427896_07d2d1",
  "meta": {
    "source": "skill:web_digest"
  },
  "path": null,
  "pubkey": "PBMCp2XBiUntTrU3C6OXrXuJv7X68LTVh1MR9gLqAtk=",
  "score": null,
  "signature": "BH+JGDXr19VZENMo9+rrwdIIu1iJsd4wvIYiUmAVvqv+mGuhXfcSjvr4emze5mag5zPo+z4miyNP61uBRLsfCA==",
  "signed_at": "2025-11-05T10:06:07Z",
  "tags": [
    "digest",
    "web",
    "news"
  ],
  "title": "Web Digest 2025-09-21 06:11",
  "url": null
}