{
  "id": "BLK_1762426448_9lvtn1",
  "title": "Web Digest 2025-11-06 11:54",
  "content": "• Hacker News: Mathematical Exploration and Discovery at Scale\n • Hacker News: Erlang Meets Idris: Cure Programming Language\n • tagesschau.de (RSS): tagesschau.de - die erste Adresse für Nachrichten und Information\n • tagesschau.de (RSS): Den Fahrzeugschein gibt es jetzt auch fürs Handy",
  "tags": [
    "digest",
    "web",
    "news"
  ],
  "url": "",
  "ts": 1762426448,
  "meta": {},
  "hash": "edc7f478ac3ba23f1a13dcf844d890f4ec1daaf9b437610ab71a56994aa20fba"
}