{
  "content": "• Hacker News: Talent Is Alignment\n • Hacker News: In Praise of RSS and Controlled Feeds of Information\n • tagesschau.de (RSS): tagesschau.de - die erste Adresse für Nachrichten und Information\n • tagesschau.de (RSS): Rückkehr der Populisten bei Wahl in Tschechien?",
  "created_at": 1759485644.1608763,
  "hash": "4dc4831ee5d51fe1e0186a012a404eafce83e89aae00fcae19f1fe9c547bd5f1",
  "id": "BLK_1759485644_f13f13",
  "meta": {
    "source": "skill:web_digest"
  },
  "path": null,
  "pubkey": "PBMCp2XBiUntTrU3C6OXrXuJv7X68LTVh1MR9gLqAtk=",
  "score": null,
  "signature": "VvBXYWML67s9t+x4E89RkZSL8ijHLZmn9PKrQe9ourxwXRnQBViYNwW0+RvdL2l7QBvWMZ2AQs9aEsCOoORHAw==",
  "signed_at": "2025-10-29T12:53:42Z",
  "tags": [
    "digest",
    "web",
    "news"
  ],
  "title": "Web Digest 2025-10-03 12:00",
  "url": null
}