{
  "content": "• Hacker News: Germany's Schleswig-Holstein Completes Migration to Open Source Email\n • Hacker News: Jeep pushed software update that bricked all 2024 Wrangler 4xe models\n • tagesschau.de (RSS): tagesschau.de - die erste Adresse für Nachrichten und Information\n • tagesschau.de (RSS): Israelische Geiseln sollen in wenigen Stunden freikommen",
  "hash": "88f1f1b02112e3761a95654496197b65cb46871a20c603059dcf13dc96f19645",
  "id": "BLK_1760283433_cic586",
  "meta": {},
  "pubkey": "PBMCp2XBiUntTrU3C6OXrXuJv7X68LTVh1MR9gLqAtk=",
  "signature": "fZB8gAmr6gmjAkS4aBzA3CeJ8qb3LvZT7OIshmNXbge7fEjn9HoYb0Zi7Zf4C+tbyLC0fY9MApF0TqZtLbA3Aw==",
  "signed_at": "2025-11-05T10:06:07Z",
  "tags": [
    "digest",
    "web",
    "news"
  ],
  "title": "Web Digest 2025-10-12 17:37",
  "ts": 1760283433,
  "url": ""
}