{
  "content": "• Hacker News: Show HN: We priced basic needs in work hours (global ranking and CSVs)\n • Hacker News: Benjie's Humanoid Olympic Games\n • tagesschau.de (RSS): tagesschau.de - die erste Adresse für Nachrichten und Information\n • tagesschau.de (RSS): Trump kündigt Treffen mit Putin in Ungarn an",
  "created_at": 1760647215.8029368,
  "hash": "72efefa881a2df9136b958118ce3b5bc861a48a9195cd968fb4860fbda1a137b",
  "id": "BLK_1760647215_0f8d05",
  "meta": {
    "source": "skill:web_digest"
  },
  "path": null,
  "pubkey": "PBMCp2XBiUntTrU3C6OXrXuJv7X68LTVh1MR9gLqAtk=",
  "score": null,
  "signature": "KAZW4r3O7emBca6lG6Mn/H9g9LNM94dZ5Fh5NWawczNVt02K+1Dks8uXk920o5hQt1XER7eqiJwnM6S2FpGcBw==",
  "signed_at": "2025-11-05T10:06:07Z",
  "tags": [
    "digest",
    "web",
    "news"
  ],
  "title": "Web Digest 2025-10-16 22:40",
  "url": null
}