{
  "content": "• Hacker News: Vibe Coding Cleanup as a Service\n • Hacker News: Representing Heterogeneous Data (2023)\n • tagesschau.de (RSS): tagesschau.de - die erste Adresse für Nachrichten und Information\n • tagesschau.de (RSS): Katerstimmung bei den Vereinten Nationen vor Vollversammlung",
  "created_at": 1758440598.396444,
  "hash": "4e6781bf36d956325b3c596a4d06ddb3559a412263b708089304694133baf2ef",
  "id": "BLK_1758440598_21d67c",
  "meta": {
    "source": "skill:web_digest"
  },
  "path": null,
  "pubkey": "PBMCp2XBiUntTrU3C6OXrXuJv7X68LTVh1MR9gLqAtk=",
  "score": null,
  "signature": "psFmyff8GOpdoD+MrPOxzY6qMwVt0MHabIGjlPhHnUKf1V13TdaBvxfZrx4RaLnj8NHpZlTASp44bEwmN6qUDg==",
  "signed_at": "2025-11-05T10:06:07Z",
  "tags": [
    "digest",
    "web",
    "news"
  ],
  "title": "Web Digest 2025-09-21 09:43",
  "url": null
}