{
  "content": "• Hacker News: Show HN: I built an 8-bit CPU simulator in Python from scratch\n • Hacker News: A sharded DuckDB on 63 nodes runs 1T row aggregation challenge in 5 sec\n • tagesschau.de (RSS): tagesschau.de - die erste Adresse für Nachrichten und Information\n • tagesschau.de (RSS): Fragen und Antworten: Wie gefährlich ist die Vogelgrippe?",
  "created_at": 1761313988.6123028,
  "hash": "5e9eac2093f9472cd268c70f3627d9f660c23f149f7807dd21298cd2398d9650",
  "id": "BLK_1761313988_a14bac",
  "meta": {
    "source": "skill:web_digest"
  },
  "path": null,
  "pubkey": "PBMCp2XBiUntTrU3C6OXrXuJv7X68LTVh1MR9gLqAtk=",
  "score": null,
  "signature": "P45IeJRuqH+BsC6nnoWGRtk59jiitLdnNd5nL+BxLP+T4OVMlFL8a+b7teib3SU4C7MuOXgZKObABEmL29DbCA==",
  "signed_at": "2025-10-24T13:53:08Z",
  "tags": [
    "digest",
    "web",
    "news"
  ],
  "title": "Web Digest 2025-10-24 15:53",
  "url": null
}