{
  "id": "BLK_1762448057_7tk75o",
  "title": "Web Digest 2025-11-06 17:54",
  "content": "• Hacker News: FBI Tries to Unmask Owner of Infamous Archive.is Site\n • Hacker News: Australia has so much solar that it's offering everyone free electricity\n • tagesschau.de (RSS): tagesschau.de - die erste Adresse für Nachrichten und Information\n • tagesschau.de (RSS): UN-Generalsekretär sieht \"tödliche Fahrlässigkeit\" bei Klimawandel",
  "tags": [
    "digest",
    "web",
    "news"
  ],
  "url": "",
  "ts": 1762448057,
  "meta": {},
  "hash": "6049fa0fca3781578b308c196d2bccd4da4a848ab9a582bb1583b0b0547c235a"
}