{
  "content": "• Hacker News: South Korea: 'many' of its nationals detained in ICE raid on GA Hyundai facility\n • Hacker News: Protobuffers Are Wrong\n • tagesschau.de (RSS): tagesschau.de - die erste Adresse für Nachrichten und Information\n • tagesschau.de (RSS): EU verhängt Milliardenstrafe gegen Google",
  "hash": "44905ba1a193851b26169b505a46a27ff2577655708062f3ede8fa5e37fdfa0a",
  "id": "BLK_1757092288_bgcgsg",
  "meta": {},
  "pubkey": "PBMCp2XBiUntTrU3C6OXrXuJv7X68LTVh1MR9gLqAtk=",
  "signature": "8Ku19jU7Qc5fqX2lNCzjpzsuGfjZ2lTw99STdMEPvoM60w6LvZPqtzAi8TKwqtsaINwOo8pE9Oir2l6QsIK3Ag==",
  "signed_at": "2025-09-21T08:13:38Z",
  "tags": [
    "digest",
    "web",
    "news"
  ],
  "title": "Web Digest 2025-09-05 19:11",
  "ts": 1757092288,
  "url": ""
}