{
  "content": "• Hacker News: Benjie's Humanoid Olympic Games\n • Hacker News: Ask HN: What in the world is going on at Supabase?\n • tagesschau.de (RSS): tagesschau.de - die erste Adresse für Nachrichten und Information\n • tagesschau.de (RSS): Trump kündigt Treffen mit Putin in Ungarn an",
  "hash": "7b8a0a06658210dfb36c0767bb8c1dc768b6d3872c42d97f41f18d74bd8f21c8",
  "id": "BLK_1760645415_6np4zb",
  "meta": {},
  "pubkey": "PBMCp2XBiUntTrU3C6OXrXuJv7X68LTVh1MR9gLqAtk=",
  "signature": "XpGRoilDYUxpelwyUvyIDphtFY38RUiVqFMheTgU2EgxukIpPmrBwZNzIqc7QUkFjKzZsiGw/H5cQwX0B4NbCQ==",
  "signed_at": "2025-11-05T10:06:06Z",
  "tags": [
    "digest",
    "web",
    "news"
  ],
  "title": "Web Digest 2025-10-16 22:10",
  "ts": 1760645415,
  "url": ""
}