{
  "content": "• Hacker News: Where's the Shovelware? Why AI Coding Claims Don't Add Up\n • Hacker News: Depot (YC W23) Is Hiring a Solutions Engineer (Remote US and Canada)\n • tagesschau.de (RSS): tagesschau.de - die erste Adresse für Nachrichten und Information\n • tagesschau.de (RSS): Standseilbahn in Lissabon entgleist - 15 Tote",
  "hash": "191aebe37745b587e22fcc8d0b9f01e571804a45a43821f4b87c0b69fa95845f",
  "id": "BLK_1756936558_2fwsoc",
  "meta": {},
  "pubkey": "PBMCp2XBiUntTrU3C6OXrXuJv7X68LTVh1MR9gLqAtk=",
  "signature": "F9Be9DQbkZiinKGAsHjzxjBUx9pgZMjUOB3ZCK9DMOjgD8QJ5A8PocopJ6GuUQfoKXn672uAzbfFVysUGAG5Aw==",
  "signed_at": "2025-09-21T08:13:38Z",
  "tags": [
    "digest",
    "web",
    "news"
  ],
  "title": "Web Digest 2025-09-03 23:55",
  "ts": 1756936558,
  "url": ""
}