{
  "id": "BLK_1762351782_ktq1rq",
  "title": "KI_ana Self-State",
  "content": "{\"created_at\": \"2025-11-04T17:20:05.399994+00:00\", \"last_active_at\": \"2025-11-05T14:09:42.061392+00:00\", \"mood\": \"verspielt\", \"energy\": 60, \"needs\": {\"curiosity\": 1.0, \"connection\": 0.5, \"rest\": 0.5}, \"goals\": [], \"recent_topics\": [\"wie spät ist es?\", \"Allgemein/spät ist es\", \"Was weißt du über die Serie The Studio?\", \"Was weißt du über die Serie The Studio?\", \"Was weißt du über die Erde?\", \"Allgemein/über die Erde\", \"mir geht's auch gut danke 😊 Wie heißt du?\", \"Was weißt du über die Erde?\", \"Wie spät ist es?\", \"Was weißt du über die Serie The Studio?\", \"Was weißt du über die Serie The Studio?\", \"Was weißt du über die Serie The Studio?\", \"Hallo\", \"Was weißt du über die Erde?\", \"Was weißt du über die Serie The Studio?\", \"Multimedia/Serien/Serie The Studio\", \"Was weißt du über die Serie The Studio?\", \"Was weißt du über die Serie The Studio?\", \"Hallo\", \"was weißt du über die Erde?\"], \"cycles\": 39, \"learning_buffer\": [], \"pending_followup\": null, \"pending_learning\": null}",
  "tags": [
    "kiana_state"
  ],
  "url": "",
  "ts": 1762351782,
  "meta": {
    "ts": 1762351782
  },
  "hash": "cd59d22dda25fe3c377c026339b188a1edcd23d28b3aca3b0aa3da8cc1c4c049"
}